cryptohands/__init__.py
cryptohands/cryptohands.py
cryptohands-0.1.0.dist-info/DESCRIPTION.rst
cryptohands-0.1.0.dist-info/METADATA
cryptohands-0.1.0.dist-info/RECORD
cryptohands-0.1.0.dist-info/WHEEL
cryptohands-0.1.0.dist-info/metadata.json
cryptohands-0.1.0.dist-info/top_level.txt
