Metadata-Version: 2.0
Name: cryptohands
Version: 0.1.0
Summary: For making Crypto Pizza
Home-page: https://github.com/chaffelson/cryptohands
Author: Daniel Chaffelson
Author-email: chaffelson@gmail.com
License: Apache Software License 2.0
Download-URL: https://github.com/Chaffelson/cryptohands/archive/0.1.0.tar.gz
Keywords: cryptohands,bitcoin,ethereum,bitfinex,poloniex,bittrex,coinbase,api,wrapper
Platform: UNKNOWN
Classifier: Development Status :: 2 - Pre-Alpha
Classifier: Intended Audience :: Developers
Classifier: License :: OSI Approved :: Apache Software License
Classifier: Natural Language :: English
Classifier: Programming Language :: Python :: 3
Classifier: Programming Language :: Python :: 3.5
Classifier: Programming Language :: Python :: 3.6
Requires-Dist: bitex
Requires-Dist: gspread
Requires-Dist: oauth2client
Requires-Dist: coinbase
Provides-Extra: dev
Requires-Dist: tox; extra == 'dev'
Requires-Dist: sphinx; extra == 'dev'
Requires-Dist: sphinx-rtd-theme; extra == 'dev'
Requires-Dist: bumpversion; extra == 'dev'
